depoc/__init__.py
depoc/_version.py
depoc/cli.py
depoc/commands/__init__.py
depoc/commands/account.py
depoc/commands/balance.py
depoc/commands/bank.py
depoc/commands/business.py
depoc/commands/contact.py
depoc/commands/customer.py
depoc/commands/finance.py
depoc/commands/inventory.py
depoc/commands/login.py
depoc/commands/logout.py
depoc/commands/me.py
depoc/commands/member.py
depoc/commands/owner.py
depoc/commands/payable.py
depoc/commands/product.py
depoc/commands/receivable.py
depoc/commands/report.py
depoc/commands/supplier.py
depoc/commands/utils/__init__.py
depoc/commands/utils/_format.py
depoc/commands/utils/_response.py
depoc/core/__init__.py
depoc/core/auth.py
depoc/core/client.py
depoc/core/requestor.py
depoc/objects/__init__.py
depoc/objects/account.py
depoc/objects/base.py
depoc/objects/business.py
depoc/objects/contact.py
depoc/objects/customer.py
depoc/objects/finance.py
depoc/objects/inventory.py
depoc/objects/member.py
depoc/objects/owner.py
depoc/objects/payment.py
depoc/objects/product.py
depoc/objects/supplier.py
depoc/objects/user.py
depoc/resources/__init__.py
depoc/resources/base.py
depoc/resources/methods.py
depoc/services/__init__.py
depoc/services/account.py
depoc/services/business.py
depoc/services/contact.py
depoc/services/customer.py
depoc/services/finance.py
depoc/services/inventory.py
depoc/services/member.py
depoc/services/owner.py
depoc/services/payable.py
depoc/services/product.py
depoc/services/receivable.py
depoc/services/supplier.py
depoc/services/user.py
depoc/utils/__init__.py
depoc/utils/_error.py
depoc/utils/_response.py
depoc/utils/_retry.py
depoc-0.1.6.dist-info/METADATA
depoc-0.1.6.dist-info/WHEEL
depoc-0.1.6.dist-info/entry_points.txt
depoc-0.1.6.dist-info/top_level.txt
depoc-0.1.6.dist-info/RECORD
