Metadata-Version: 2.2
Name: depoc
Version: 0.1.6
Summary: Python bindings for the Depoc API
Home-page: https://github.com/hugobelem/depoc-api
Author: Hugo Belém
License: MIT
Requires-Python: >=3.12
Requires-Dist: requests>=2.32.3
Requires-Dist: click>=8.1.8
Requires-Dist: appdirs>=1.4.4
Requires-Dist: rich>=13.9.4
Dynamic: author
Dynamic: description
Dynamic: description-content-type
Dynamic: home-page
Dynamic: license
Dynamic: requires-dist
Dynamic: requires-python
Dynamic: summary
